eljson/__init__.py
eljson/exceptions.py
eljson/json.py
eljson/json_doc.py
eljson/py.typed
eljson/strict_json.py
eljson-0.0.1.dist-info/LICENSE
eljson-0.0.1.dist-info/METADATA
eljson-0.0.1.dist-info/WHEEL
eljson-0.0.1.dist-info/RECORD
