Metadata-Version: 2.1
Name: eljson
Version: 0.0.1
Summary: This is how python package should look like!
Home-page: https://github.com/blablatdinov/eljson
License: MIT
Author: Almaz Ilaletdinov
Author-email: a.ilaletdinov@yandex.ru
Requires-Python: >=3.9,<4.0
Classifier: Development Status :: 3 - Alpha
Classifier: Intended Audience :: Developers
Classifier: License :: OSI Approved :: MIT License
Classifier: Operating System :: OS Independent
Classifier: Programming Language :: Python :: 3
Classifier: Programming Language :: Python :: 3.9
Classifier: Programming Language :: Python :: 3.10
Classifier: Programming Language :: Python :: 3.11
Classifier: Programming Language :: Python :: 3.12
Classifier: Topic :: Software Development :: Libraries :: Python Modules
Requires-Dist: attrs (>=22.2.0)
Requires-Dist: jsonpath-ng
Requires-Dist: jsonschema (>=0.3)
Requires-Dist: ujson (>=1.19)
Project-URL: Repository, https://github.com/blablatdinov/eljson
